seqrep/__init__.py
seqrep/evaluation.py
seqrep/feature_engineering.py
seqrep/feature_reduction.py
seqrep/labeling.py
seqrep/pipeline_evaluation.py
seqrep/scaling.py
seqrep/splitting.py
seqrep/utils.py
seqrep-0.0.2.dist-info/LICENSE
seqrep-0.0.2.dist-info/METADATA
seqrep-0.0.2.dist-info/WHEEL
seqrep-0.0.2.dist-info/top_level.txt
seqrep-0.0.2.dist-info/RECORD
