Metadata-Version: 2.1
Name: seqrep
Version: 0.0.2
Summary: Scientific framework for representation in sequential data
Home-page: https://github.com/MIR-MU/seqrep
Author: Jakub Rysavy
Author-email: jakubrysavy00@gmail.com
License: MIT
Platform: UNKNOWN
License-File: LICENSE
Requires-Dist: hrv-analysis (>=1.0.4)
Requires-Dist: numpy-ext (>=0.9.6)
Requires-Dist: pandas (>=1.1.5)
Requires-Dist: pandas-ta (>=0.3.14b0)
Requires-Dist: plotly (>=4.4.1)
Requires-Dist: scikit-learn (>=1.0.1)
Requires-Dist: ta (>=0.8.0)
Requires-Dist: tqdm (>=4.62.3)
